Hoyong0604Test/test1.py
Hoyong0604Test/test2.py
Hoyong0604Test-0.0.0.2.dist-info/METADATA
Hoyong0604Test-0.0.0.2.dist-info/WHEEL
Hoyong0604Test-0.0.0.2.dist-info/top_level.txt
Hoyong0604Test-0.0.0.2.dist-info/RECORD
